typer_model_args/__init__.py
typer_model_args/_annotations.py
typer_model_args/_kwargs.py
typer_model_args/decorator.py
typer_model_args-0.3.2.dist-info/METADATA
typer_model_args-0.3.2.dist-info/WHEEL
typer_model_args-0.3.2.dist-info/licenses/LICENSE
typer_model_args-0.3.2.dist-info/RECORD
