Metadata-Version: 2.4
Name: typer_model_args
Version: 0.3.2
Summary: Extensions for the python typer library
Project-URL: Source, https://github.com/juliushetzel/typer-model-args
Author-email: juliushetzel <mail@juliushetzel.com>
License: MIT
License-File: LICENSE
Requires-Python: >=3.9
Requires-Dist: pydantic>=2.1.1
Requires-Dist: typer>=0.16.1
